evo2_mcp/__init__.py
evo2_mcp/dummy_evo2.py
evo2_mcp/main.py
evo2_mcp/mcp.py
evo2_mcp/model.py
evo2_mcp/tools/__init__.py
evo2_mcp/tools/_evo2.py
evo2_mcp/tools/layers.json
evo2_mcp-0.2.2.dist-info/METADATA
evo2_mcp-0.2.2.dist-info/WHEEL
evo2_mcp-0.2.2.dist-info/entry_points.txt
evo2_mcp-0.2.2.dist-info/licenses/LICENSE
evo2_mcp-0.2.2.dist-info/RECORD
