Metadata-Version: 2.4
Name: evo2_mcp
Version: 0.2.2
Summary: MCP server for generating, scoring and embedding genomic sequences using Evo 2
Project-URL: Documentation, https://evo2-mcp.readthedocs.io/
Project-URL: Homepage, https://github.com/not-a-feature/evo2-mcp
Project-URL: Source, https://github.com/not-a-feature/evo2-mcp
Project-URL: Bug Tracker, https://github.com/not-a-feature/evo2-mcp/issues
Project-URL: Changelog, https://evo2-mcp.readthedocs.io/en/latest/changelog.html
Project-URL: BioContextAI, https://biocontext.ai/registry/not-a-feature/evo2-mcp
Author: Jules Kreuer
Maintainer-email: Jules Kreuer <jules.kreuer@uni-tuebingen.de>
License:                    GNU LESSER GENERAL PUBLIC LICENSE
License-File: LICENSE
Keywords: bioinformatics,deep-learning,embeddings,evo2,genomics,mcp,model-context-protocol,sequence-generation
Classifier: Development Status :: 4 - Beta
Classifier: Intended Audience :: Developers
Classifier: Intended Audience :: Science/Research
Classifier: License :: OSI Approved :: GNU Lesser General Public License v3 (LGPLv3)
Classifier: Operating System :: OS Independent
Classifier: Programming Language :: Python :: 3 :: Only
Classifier: Programming Language :: Python :: 3.12
Classifier: Programming Language :: Python :: 3.13
Classifier: Topic :: Scientific/Engineering :: Artificial Intelligence
Classifier: Topic :: Scientific/Engineering :: Bio-Informatics
Requires-Python: >=3.12
Requires-Dist: click
Requires-Dist: fastmcp
Requires-Dist: numpy
Requires-Dist: torch
Provides-Extra: dev
Requires-Dist: pre-commit; extra == 'dev'
Requires-Dist: twine>=4.0.2; extra == 'dev'
Provides-Extra: doc
Requires-Dist: docutils!=0.18.*,!=0.19.*,>=0.8; extra == 'doc'
Requires-Dist: ipykernel; extra == 'doc'
Requires-Dist: ipython; extra == 'doc'
Requires-Dist: myst-nb>=1.1; extra == 'doc'
Requires-Dist: pandas; extra == 'doc'
Requires-Dist: setuptools; extra == 'doc'
Requires-Dist: sphinx-autoapi; extra == 'doc'
Requires-Dist: sphinx-book-theme>=1; extra == 'doc'
Requires-Dist: sphinx-copybutton; extra == 'doc'
Requires-Dist: sphinx-tabs; extra == 'doc'
Requires-Dist: sphinx>=8.1; extra == 'doc'
Requires-Dist: sphinxext-opengraph; extra == 'doc'
Provides-Extra: evo2
Requires-Dist: evo2; extra == 'evo2'
Provides-Extra: test
Requires-Dist: coverage; extra == 'test'
Requires-Dist: pytest; extra == 'test'
Requires-Dist: pytest-asyncio; extra == 'test'
